mdpython/__init__.py
mdpython/account/__init__.py
mdpython/account/reconcile.py
mdpython/datautils/__init__.py
mdpython/datautils/jsonutil.py
mdpython/datautils/table.py
mdpython/debugutils/__init__.py
mdpython/debugutils/curpos.py
mdpython/debugutils/find.py
mdpython/debugutils/timer.py
mdpython/debugutils/version.py
mdpython/docutils/__init__.py
mdpython/docutils/pdf.py
mdpython/docutils/project.py
mdpython/docutils/testcase.py
mdpython/fileutils/__init__.py
mdpython/fileutils/cleanup.py
mdpython/fileutils/compare.py
mdpython/fileutils/compare_dir.py
mdpython/fileutils/dir_info.py
mdpython/fileutils/excel.py
mdpython/fileutils/html_template.py
mdpython/netutils/__init__.py
mdpython/netutils/port.py
mdpython/uiutils/__init__.py
mdpython/uiutils/menu_based_app.py
mdpython-0.0.29.dist-info/METADATA
mdpython-0.0.29.dist-info/WHEEL
mdpython-0.0.29.dist-info/RECORD
