Metadata-Version: 2.4
Name: mdpython
Version: 0.0.29
Summary: MD Python Library - High level library for common use cases
Author-email: Dhaval <seedhaval@gmail.com>
Classifier: License :: OSI Approved :: BSD License
Classifier: Operating System :: OS Independent
Classifier: Programming Language :: Python :: 3
Requires-Python: >=3.8
Requires-Dist: ollama
Requires-Dist: openpyxl
Requires-Dist: pandas
Requires-Dist: psutil
Requires-Dist: pypdf2
Requires-Dist: reportlab
